[
null,
{"id":1,"expanded":true,"name":"Level 4","order":6,"parentId":0,"scrollX":2725.090909090909,"scrollY":1697.4545454545455,"quick":false},
{"id":2,"expanded":true,"name":"Level 7","order":9,"parentId":0,"scrollX":2744.727272727273,"scrollY":3087.2727272727275,"quick":false},
{"id":3,"expanded":true,"name":"Level 9","order":11,"parentId":0,"scrollX":2533.090909090909,"scrollY":3019.636363636364,"quick":false},
{"id":4,"expanded":true,"name":"Level 2","order":4,"parentId":0,"scrollX":2943.2727272727275,"scrollY":2225.4545454545455,"quick":false},
{"id":5,"expanded":true,"name":"Level 8","order":10,"parentId":0,"scrollX":2354.6666666666665,"scrollY":3384,"quick":false},
{"id":6,"expanded":false,"name":"Level 0","order":2,"parentId":0,"scrollX":1503.2727272727273,"scrollY":1998.5454545454547,"quick":false},
{"id":7,"expanded":true,"name":"Level 15","order":14,"parentId":0,"scrollX":2943.2727272727275,"scrollY":2079.2727272727275,"quick":false},
{"id":8,"expanded":true,"name":"Level 1","order":3,"parentId":0,"scrollX":1046.4,"scrollY":2964.8,"quick":false},
{"id":9,"expanded":true,"name":"Level 10","order":12,"parentId":0,"scrollX":3093.818181818182,"scrollY":1828.363636363636,"quick":false},
{"id":10,"expanded":true,"name":"Level 5","order":7,"parentId":0,"scrollX":2314.909090909091,"scrollY":1014.5454545454546,"quick":false},
{"id":11,"expanded":true,"name":"Level 6","order":8,"parentId":0,"scrollX":2877.3333333333335,"scrollY":1909.3333333333333,"quick":false},
{"id":12,"expanded":true,"name":"Level Base","order":15,"parentId":0,"scrollX":3302.3999999999996,"scrollY":2539.2,"quick":false},
{"id":13,"expanded":true,"name":"Level 11","order":13,"parentId":0,"scrollX":3449.4545454545455,"scrollY":2177.4545454545455,"quick":false},
{"id":14,"expanded":true,"name":"Level 3","order":5,"parentId":0,"scrollX":2070.5454545454545,"scrollY":1315.6363636363637,"quick":false},
{"id":15,"expanded":false,"name":"Intro","order":1,"parentId":0,"scrollX":1650.6666666666667,"scrollY":912,"quick":false}
]